RuanjianGongchengshiRuanJinengZhiYufaJulebu/README.md
RuanjianGongchengshiRuanJinengZhiYufaJulebu/__init__.py
RuanjianGongchengshiRuanJinengZhiYufaJulebu/__main__.py
RuanjianGongchengshiRuanJinengZhiYufaJulebu/file.epub
RuanjianGongchengshiRuanJinengZhiYufaJulebu/index.html
RuanjianGongchengshiRuanJinengZhiYufaJulebu/css/__init__.py
RuanjianGongchengshiRuanJinengZhiYufaJulebu/css/annotations.css
RuanjianGongchengshiRuanJinengZhiYufaJulebu/css/main.css
RuanjianGongchengshiRuanJinengZhiYufaJulebu/css/normalize.css
RuanjianGongchengshiRuanJinengZhiYufaJulebu/css/popup.css
RuanjianGongchengshiRuanJinengZhiYufaJulebu/font/__init__.py
RuanjianGongchengshiRuanJinengZhiYufaJulebu/font/fontello.eot
RuanjianGongchengshiRuanJinengZhiYufaJulebu/font/fontello.svg
RuanjianGongchengshiRuanJinengZhiYufaJulebu/font/fontello.ttf
RuanjianGongchengshiRuanJinengZhiYufaJulebu/font/fontello.woff
RuanjianGongchengshiRuanJinengZhiYufaJulebu/img/__init__.py
RuanjianGongchengshiRuanJinengZhiYufaJulebu/img/annotator-glyph-sprite.png
RuanjianGongchengshiRuanJinengZhiYufaJulebu/img/annotator-icon-sprite.png
RuanjianGongchengshiRuanJinengZhiYufaJulebu/img/apple-touch-icon.png
RuanjianGongchengshiRuanJinengZhiYufaJulebu/img/cancelfullscreen.png
RuanjianGongchengshiRuanJinengZhiYufaJulebu/img/close.png
RuanjianGongchengshiRuanJinengZhiYufaJulebu/img/fullscreen.png
RuanjianGongchengshiRuanJinengZhiYufaJulebu/img/loader.gif
RuanjianGongchengshiRuanJinengZhiYufaJulebu/img/menu-icon.png
RuanjianGongchengshiRuanJinengZhiYufaJulebu/img/save.png
RuanjianGongchengshiRuanJinengZhiYufaJulebu/img/saved.png
RuanjianGongchengshiRuanJinengZhiYufaJulebu/img/settings-s.png
RuanjianGongchengshiRuanJinengZhiYufaJulebu/img/settings.png
RuanjianGongchengshiRuanJinengZhiYufaJulebu/img/star.png
RuanjianGongchengshiRuanJinengZhiYufaJulebu/js/__init__.py
RuanjianGongchengshiRuanJinengZhiYufaJulebu/js/epub.js
RuanjianGongchengshiRuanJinengZhiYufaJulebu/js/epub.min.js
ruanjian_gongchengshi_ruan_jineng_zhi_yufa_julebu-2024.3.4.0.dist-info/METADATA
ruanjian_gongchengshi_ruan_jineng_zhi_yufa_julebu-2024.3.4.0.dist-info/WHEEL
ruanjian_gongchengshi_ruan_jineng_zhi_yufa_julebu-2024.3.4.0.dist-info/entry_points.txt
ruanjian_gongchengshi_ruan_jineng_zhi_yufa_julebu-2024.3.4.0.dist-info/top_level.txt
ruanjian_gongchengshi_ruan_jineng_zhi_yufa_julebu-2024.3.4.0.dist-info/RECORD
